mytorch/__init__.py
mytorch/ops/__init__.py
mytorch/ops/im2col.py
python_mytorch-0.1.2.dist-info/METADATA
python_mytorch-0.1.2.dist-info/WHEEL
python_mytorch-0.1.2.dist-info/top_level.txt
python_mytorch-0.1.2.dist-info/RECORD
