Metadata-Version: 2.1
Name: python-mytorch
Version: 0.1.2
Summary: A Library extending PyTorch for Personal Needs backed by C++/CUDA APIs
Home-page: https://github.com/Syzygianinfern0/MyTorch.git
Author: S P Sharan
Author-email: spsharan2000@gmail.com
License: UNKNOWN
Platform: UNKNOWN
